da_rnn/__init__.py
da_rnn/common.py
da_rnn/darnn.py
da_rnn/layers.py
da_rnn/model.py
da_rnn/keras/__init__.py
da_rnn/keras/layers.py
da_rnn/keras/model.py
da_rnn/torch/__init__.py
da_rnn/torch/model.py
da_rnn-1.0.2.dist-info/LICENSE
da_rnn-1.0.2.dist-info/METADATA
da_rnn-1.0.2.dist-info/WHEEL
da_rnn-1.0.2.dist-info/top_level.txt
da_rnn-1.0.2.dist-info/RECORD
