Metadata-Version: 2.1
Name: da-rnn
Version: 1.0.2
Summary: A tensorflow 2.0 implementation of the Dual-Stage Attention-Based Recurrent Neural Network for Time Series Prediction
Home-page: https://github.com/kaelzhang/tensorflow-2.0-DA-RNN
Author: kaelzhang
Author-email: 
License: MIT
Keywords: da_rnn
Platform: UNKNOWN
Classifier: Topic :: Software Development :: Libraries :: Python Modules
Classifier: Programming Language :: Python :: 3.7
Classifier: Programming Language :: Python :: 3.8
Classifier: Programming Language :: Python :: Implementation :: PyPy
Classifier: Topic :: Software Development :: Libraries :: Python Modules
Classifier: License :: OSI Approved :: MIT License
Requires-Python: >=3.7
Requires-Dist: numpy (<=1.19.5)
Provides-Extra: keras
Requires-Dist: tensorflow (>=2) ; extra == 'keras'
Provides-Extra: torch
Requires-Dist: torch ; extra == 'torch'
